dolfin_estim/FEMU.py
dolfin_estim/__init__.py
dolfin_estim/equilibrium_gap.py
dolfin_estim/get_measured_disp.py
dolfin_estim/starting_estimation.py
dolfin_estim/virtual_fields_method.py
dolfin_estim/virtual_fields_method_plane_wave.py
dolfin_estim-2024.7.25.post2.dist-info/LICENSE
dolfin_estim-2024.7.25.post2.dist-info/METADATA
dolfin_estim-2024.7.25.post2.dist-info/WHEEL
dolfin_estim-2024.7.25.post2.dist-info/top_level.txt
dolfin_estim-2024.7.25.post2.dist-info/RECORD
