Metadata-Version: 2.1
Name: dolfin_estim
Version: 2024.7.25.post2
Home-page: https://gitlab.inria.fr/apeyraut/dolfin_estim
Author: Alice Peyraut
Author-email: alice.peyraut@polytechnique.edu
License: GPLv3
Classifier: Programming Language :: Python :: 3
Classifier: License :: OSI Approved :: GNU General Public License v3 (GPLv3)
Classifier: Operating System :: OS Independent
License-File: LICENSE
Requires-Dist: meshio
Requires-Dist: numpy
Requires-Dist: scipy
Requires-Dist: fire
Requires-Dist: ufl
Requires-Dist: dolfin-mech
Requires-Dist: dolfin-warp
